InstahackWasii/AppInfo.py
InstahackWasii/InstahackWasiiCLI.py
InstahackWasii/InstahackWasiiConfigurationCreator.py
InstahackWasii/InstahackWasiiDumper.py
InstahackWasii/InstahackWasiiInstance.py
InstahackWasii/InstahackWasiiPortable.py
InstahackWasii/InstahackWasiiScript.py
InstahackWasii/InstahackWasiiSession.py
InstahackWasii/__init__.py
InstahackWasii/colors/__init__.py
InstahackWasii/colors/ansi.py
InstahackWasii/colors/ansitowin32.py
InstahackWasii/colors/initialise.py
InstahackWasii/colors/win32.py
InstahackWasii/colors/winterm.py
hackerwasii-2.0.7.dist-info/LICENSE
hackerwasii-2.0.7.dist-info/METADATA
hackerwasii-2.0.7.dist-info/WHEEL
hackerwasii-2.0.7.dist-info/entry_points.txt
hackerwasii-2.0.7.dist-info/top_level.txt
hackerwasii-2.0.7.dist-info/RECORD
