Metadata-Version: 2.1
Name: hackerwasii
Version: 2.0.7
Summary: instahack is a bash based script which is officially made to test password strength of instagram account from termux with bruteforce attack and. This tool works on both rooted Android device and Non-rooted Android device.
Home-page: https://github.com/evildevill/instahack
Download-URL: https://github.com/evildevill/instahack/archive/v2.0.7.tar.gz
Author: Waseem Akram
Author-email: Waseem Akram <hackerwasi1@gmail.com>
License: MIT License        
Project-URL: Homepage, https://github.com/evildevill/instahack
Project-URL: Bug Tracker, https://github.com/evildevill/instahack/issues
Keywords: cli,hack,instagram,with,out,password,limit,brute,force,attack,instagram,instahack,evildevill,hackerwasii
Classifier: Programming Language :: Python :: 3
Classifier: License :: OSI Approved :: MIT License
Classifier: Operating System :: OS Independent
Requires-Python: >=3.7
License-File: LICENSE
Requires-Dist: requests
Requires-Dist: requests[socks]
Requires-Dist: stem
